gchatcardbuilder/__init__.py
gchatcardbuilder/card_builder.py
gchatcardbuilder/card_builder_base.py
gchatcardbuilder/card_builder_v2.py
gchatcardbuilder/utils.py
gchatcardbuilder/versions/__init__.py
gchatcardbuilder/versions/v2/__init__.py
gchatcardbuilder/versions/v2/root.py
gchatcardbuilder/versions/v2/widgets/__init__.py
gchatcardbuilder/versions/v2/widgets/enums.py
gchatcardbuilder/versions/v2/widgets/widgets.py
tests/__init__.py
tests/test_v2_builder.py
gchatcardbuilder-0.1.7.dist-info/LICENSE
gchatcardbuilder-0.1.7.dist-info/METADATA
gchatcardbuilder-0.1.7.dist-info/WHEEL
gchatcardbuilder-0.1.7.dist-info/top_level.txt
gchatcardbuilder-0.1.7.dist-info/RECORD
