Metadata-Version: 2.1
Name: gchatcardbuilder
Version: 0.1.7
Summary: A clean, type-safe interface for generating rich chat responses to the Google Chat API using the CardsV2 schema.
Home-page: https://github.com/pkarl/gchatcardbuilder
Author: Pete Karl II
Author-email: pete.karl@gmail.com
Keywords: google chat api,cardsv2,gchat,chatbot,chat bot,google chat
Classifier: Development Status :: 4 - Beta
Classifier: Intended Audience :: Developers
Classifier: Topic :: Software Development :: Libraries
Classifier: License :: OSI Approved :: Apache Software License
Classifier: Programming Language :: Python :: 3.10
Classifier: Programming Language :: Python :: 3.11
License-File: LICENSE
